skip_gram/__init__.py
skip_gram/__main__.py
skip_gram/cbow.py
skip_gram/huffman.py
skip_gram/model.py
skip_gram/train.py
skip_gram-0.1.2.dist-info/licenses/LICENSE.txt
skip_gram-0.1.2.dist-info/METADATA
skip_gram-0.1.2.dist-info/WHEEL
skip_gram-0.1.2.dist-info/top_level.txt
skip_gram-0.1.2.dist-info/RECORD
